{
  "type": {
    "MONEY": {
      "title": "srng.booster.money.title",
      "content": "booster.money.content",
      "color": {
        "hex": "#A9823F"
      },
      "emoji": "\uE0FC",
      "isVisible": true,
      "isMultipliedBy": true
    },
    "LUCK": {
      "title": "srng.booster.luck.title",
      "content": "booster.luck.content",
      "color": {
        "hex": "#5F8A62"
      },
      "emoji": "\uE040",
      "isVisible": true,
      "isMultipliedBy": true
    },
    "DAMAGE": {
      "title": "srng.booster.damage.title",
      "content": "booster.damage.content",
      "color": {
        "hex": "#4F6F8F"
      },
      "emoji": "\uE147",
      "isVisible": true,
      "isMultipliedBy": true
    },
    "HEALTH": {
      "title": "srng.booster.health.title",
      "content": "booster.health.content",
      "color": {
        "hex": "#A84A4A"
      },
      "emoji": "\uE19A",
      "isVisible": true,
      "isMultipliedBy": true
    },
    "ROLL_SPEED": {
      "title": "srng.booster.roll_speed.title",
      "content": "booster.health.content",
      "color": {
        "hex": "#808080"
      },
      "emoji": "\uE19A",
      "isVisible": true,
      "isMultipliedBy": true
    }
  }
}