{
  "rollDuration": 75,
  "slimes": {
    "WOLF": {
      "chance": 50.0
    },
    "BLACK_CAT": {
      "chance": 25.0
    },
    "BEAR": {
      "chance": 10.0
    },
    "TURTLE": {
      "chance": 5.1
    },
    "LEPRECHAUN": {
      "chance": 4.9
    }
  },
  "message": {
    "roll": {
      "wait": {
        "message": "Текущий ролл не завершился",
        "duration": 2.0
      },
      "startRoll": {
        "title": "Slime RNG",
        "description": "Вы начали крутить слайма",
        "duration": 2.0
      },
      "getNewSlime": {
        "itemStack": {
          "type": "SLIME_BALL"
        },
        "title": "Вы получили нового слайма",
        "duration": 2.5
      }
    },
    "equipmentMenu": {
      "rolling": {
        "message": "Вы не можете открыть меню во время прокрутки",
        "duration": 2.0
      },
      "successEquip": {
        "message": "Слайм успешно экипирован",
        "duration": 2.0
      },
      "successUnequip": {
        "message": "Слайм успешно снят",
        "duration": 2.0
      },
      "noSlimes": {
        "message": "У вас нет слаймов, используйте /roll",
        "duration": 2.0
      },
      "alreadyEquipped": {
        "message": "Этот слайм уже выбран",
        "duration": 2.0
      },
      "notEquipped": {
        "message": "Этот слайм не надет",
        "duration": 2.0
      }
    }
  }
}