{
  "blocksLimit": 200,
  "logEvery": 3,
  "logTelegramChat": -809189525,
  "locations": {
    "1": {
      "layers": {
        "215-219": {
          "blocks": {
            "SANDSTONE": {
              "data": 0,
              "hardness": 5,
              "replace": 120,
              "keys": {
                "DEFAULT": 0.25,
                "PET": 0.125
              }
            }
          }
        },
        "210-214": {
          "blocks": {
            "SANDSTONE": {
              "data": 0,
              "hardness": 7,
              "replace": 120,
              "keys": {
                "DEFAULT": 0.25,
                "PET": 0.125
              }
            }
          }
        },
        "205-209": {
          "blocks": {
            "SANDSTONE": {
              "data": 0,
              "hardness": 10,
              "replace": 120,
              "keys": {
                "DEFAULT": 0.25,
                "PET": 0.125
              }
            }
          }
        },
        "200-204": {
          "blocks": {
            "SANDSTONE": {
              "data": 0,
              "hardness": 10,
              "replace": 120,
              "keys": {
                "DEFAULT": 0.25,
                "PET": 0.125
              }
            }
          }
        },
        "195-199": {
          "blocks": {
            "SANDSTONE": {
              "data": 0,
              "hardness": 10,
              "replace": 120,
              "keys": {
                "DEFAULT": 0.25,
                "PET": 0.125
              }
            }
          }
        },
        "190-194": {
          "blocks": {
            "SANDSTONE": {
              "data": 0,
              "hardness": 15,
              "replace": 120,
              "keys": {
                "DEFAULT": 0.25,
                "PET": 0.125
              }
            }
          }
        },
        "185-189": {
          "blocks": {
            "SANDSTONE": {
              "data": 0,
              "hardness": 20,
              "replace": 120,
              "keys": {
                "DEFAULT": 0.25,
                "PET": 0.125
              }
            }
          }
        },
        "180-184": {
          "blocks": {
            "SANDSTONE": {
              "data": 0,
              "hardness": 25,
              "replace": 120,
              "keys": {
                "DEFAULT": 0.25,
                "PET": 0.125
              }
            }
          }
        },
        "175-179": {
          "blocks": {
            "SANDSTONE": {
              "data": 0,
              "hardness": 30,
              "replace": 120,
              "keys": {
                "DEFAULT": 0.25,
                "PET": 0.125
              }
            }
          }
        },
        "170-174": {
          "blocks": {
            "SANDSTONE": {
              "data": 0,
              "hardness": 35,
              "replace": 120,
              "keys": {
                "DEFAULT": 0.25,
                "PET": 0.125
              }
            }
          }
        },
        "165-169": {
          "blocks": {
            "SANDSTONE": {
              "data": 0,
              "hardness": 40,
              "replace": 120,
              "keys": {
                "DEFAULT": 0.25,
                "PET": 0.125
              }
            }
          }
        },
        "160-164": {
          "blocks": {
            "SANDSTONE": {
              "data": 0,
              "hardness": 45,
              "replace": 120,
              "keys": {
                "DEFAULT": 0.25,
                "PET": 0.125
              }
            }
          }
        },
        "155-159": {
          "blocks": {
            "SANDSTONE": {
              "data": 0,
              "hardness": 50,
              "replace": 120,
              "keys": {
                "DEFAULT": 0.25,
                "PET": 0.125
              }
            }
          }
        },
        "150-154": {
          "blocks": {
            "SANDSTONE": {
              "data": 0,
              "hardness": 60,
              "replace": 120,
              "keys": {
                "DEFAULT": 0.25,
                "PET": 0.125
              }
            }
          }
        },
        "145-149": {
          "blocks": {
            "SANDSTONE": {
              "data": 0,
              "hardness": 70,
              "replace": 120,
              "keys": {
                "DEFAULT": 0.25,
                "PET": 0.125
              }
            }
          }
        },
        "140-144": {
          "blocks": {
            "SANDSTONE": {
              "data": 0,
              "hardness": 80,
              "replace": 120,
              "keys": {
                "DEFAULT": 0.25,
                "PET": 0.125
              }
            }
          }
        },
        "135-139": {
          "blocks": {
            "SANDSTONE": {
              "data": 0,
              "hardness": 90,
              "replace": 120,
              "keys": {
                "DEFAULT": 0.25,
                "PET": 0.125
              }
            }
          }
        },
        "130-134": {
          "blocks": {
            "SANDSTONE": {
              "data": 0,
              "hardness": 100,
              "replace": 120,
              "keys": {
                "DEFAULT": 0.25,
                "PET": 0.125
              }
            }
          }
        },
        "125-129": {
          "blocks": {
            "SANDSTONE": {
              "data": 0,
              "hardness": 125,
              "replace": 120,
              "keys": {
                "DEFAULT": 0.25,
                "PET": 0.125
              }
            }
          }
        },
        "120-124": {
          "blocks": {
            "SANDSTONE": {
              "data": 0,
              "hardness": 150,
              "replace": 120,
              "keys": {
                "DEFAULT": 0.25,
                "PET": 0.125
              }
            }
          }
        },
        "115-119": {
          "blocks": {
            "SANDSTONE": {
              "data": 0,
              "hardness": 250,
              "replace": 120,
              "keys": {
                "DEFAULT": 0.25,
                "PET": 0.125
              }
            }
          }
        },
        "110-114": {
          "blocks": {
            "SANDSTONE": {
              "data": 0,
              "hardness": 350,
              "replace": 120,
              "keys": {
                "DEFAULT": 0.25,
                "PET": 0.125
              }
            }
          }
        },
        "105-109": {
          "blocks": {
            "SANDSTONE": {
              "data": 0,
              "hardness": 450,
              "replace": 120,
              "keys": {
                "DEFAULT": 0.25,
                "PET": 0.125
              }
            }
          }
        },
        "100-104": {
          "blocks": {
            "SANDSTONE": {
              "data": 0,
              "hardness": 500,
              "replace": 120,
              "keys": {
                "DEFAULT": 0.25,
                "PET": 0.125
              }
            }
          }
        }
      }
    },
    "2": {
      "layers": {
        "83-87": {
          "blocks": {
            "NETHERRACK": {
              "hardness": 15,
              "data": 0,
              "replace": 120,
              "keys": {
                "DEFAULT": 0.3,
                "PET": 0.15
              }
            }
          }
        },
        "78-82": {
          "blocks": {
            "NETHERRACK": {
              "hardness": 40,
              "data": 0,
              "replace": 120,
              "keys": {
                "DEFAULT": 0.3,
                "PET": 0.15
              }
            }
          }
        },
        "73-77": {
          "blocks": {
            "NETHERRACK": {
              "hardness": 65,
              "data": 0,
              "replace": 120,
              "keys": {
                "DEFAULT": 0.3,
                "PET": 0.15
              }
            }
          }
        },
        "68-72": {
          "blocks": {
            "NETHERRACK": {
              "hardness": 80,
              "data": 0,
              "replace": 120,
              "keys": {
                "DEFAULT": 0.3,
                "PET": 0.15
              }
            }
          }
        },
        "63-67": {
          "blocks": {
            "NETHERRACK": {
              "hardness": 105,
              "data": 0,
              "replace": 120,
              "keys": {
                "DEFAULT": 0.3,
                "PET": 0.15
              }
            }
          }
        },
        "58-62": {
          "blocks": {
            "NETHERRACK": {
              "hardness": 130,
              "data": 0,
              "replace": 120,
              "keys": {
                "DEFAULT": 0.3,
                "PET": 0.15
              }
            }
          }
        },
        "53-57": {
          "blocks": {
            "NETHERRACK": {
              "hardness": 150,
              "data": 0,
              "replace": 120,
              "keys": {
                "DEFAULT": 0.3,
                "PET": 0.15
              }
            }
          }
        },
        "48-52": {
          "blocks": {
            "NETHERRACK": {
              "hardness": 200,
              "data": 0,
              "replace": 120,
              "keys": {
                "DEFAULT": 0.3,
                "PET": 0.15
              }
            }
          }
        },
        "43-47": {
          "blocks": {
            "NETHERRACK": {
              "hardness": 250,
              "data": 0,
              "replace": 120,
              "keys": {
                "DEFAULT": 0.3,
                "PET": 0.15
              }
            }
          }
        },
        "38-42": {
          "blocks": {
            "NETHERRACK": {
              "hardness": 300,
              "data": 0,
              "replace": 120,
              "keys": {
                "DEFAULT": 0.3,
                "PET": 0.15
              }
            }
          }
        },
        "33-37": {
          "blocks": {
            "NETHERRACK": {
              "hardness": 350,
              "data": 0,
              "replace": 120,
              "keys": {
                "DEFAULT": 0.3,
                "PET": 0.15
              }
            }
          }
        },
        "28-32": {
          "blocks": {
            "NETHERRACK": {
              "hardness": 450,
              "data": 0,
              "replace": 120,
              "keys": {
                "DEFAULT": 0.3,
                "PET": 0.15
              }
            }
          }
        },
        "23-27": {
          "blocks": {
            "NETHERRACK": {
              "hardness": 750,
              "data": 0,
              "replace": 120,
              "keys": {
                "DEFAULT": 0.3,
                "PET": 0.15
              }
            }
          }
        },
        "18-22": {
          "blocks": {
            "NETHERRACK": {
              "hardness": 1050,
              "data": 0,
              "replace": 120,
              "keys": {
                "DEFAULT": 0.3,
                "PET": 0.15
              }
            }
          }
        },
        "13-17": {
          "blocks": {
            "NETHERRACK": {
              "hardness": 1400,
              "data": 0,
              "replace": 120,
              "keys": {
                "DEFAULT": 0.3,
                "PET": 0.15
              }
            }
          }
        },
        "8-12": {
          "blocks": {
            "NETHERRACK": {
              "hardness": 1500,
              "data": 0,
              "replace": 120,
              "keys": {
                "DEFAULT": 0.3,
                "PET": 0.15
              }
            }
          }
        },
        "5-7": {
          "blocks": {
            "NETHERRACK": {
              "hardness": 1600,
              "data": 0,
              "replace": 120,
              "keys": {
                "DEFAULT": 0.3,
                "PET": 0.15
              }
            }
          }
        }
      }
    },
    "3": {
      "layers": {
        "204-208": {
          "blocks": {
            "PACKED_ICE": {
              "hardness": 20,
              "data": 0,
              "replace": 120,
              "keys": {
                "DEFAULT": 0.35,
                "PET": 0.175
              }
            }
          }
        },
        "199-203": {
          "blocks": {
            "PACKED_ICE": {
              "hardness": 50,
              "data": 0,
              "replace": 120,
              "keys": {
                "DEFAULT": 0.35,
                "PET": 0.175
              }
            }
          }
        },
        "194-198": {
          "blocks": {
            "PACKED_ICE": {
              "hardness": 100,
              "data": 0,
              "replace": 120,
              "keys": {
                "DEFAULT": 0.35,
                "PET": 0.175
              }
            }
          }
        },
        "189-193": {
          "blocks": {
            "PACKED_ICE": {
              "hardness": 125,
              "data": 0,
              "replace": 120,
              "keys": {
                "DEFAULT": 0.35,
                "PET": 0.175
              }
            }
          }
        },
        "184-188": {
          "blocks": {
            "PACKED_ICE": {
              "hardness": 150,
              "data": 0,
              "replace": 120,
              "keys": {
                "DEFAULT": 0.35,
                "PET": 0.175
              }
            }
          }
        },
        "177-183": {
          "blocks": {
            "PACKED_ICE": {
              "hardness": 160,
              "data": 0,
              "replace": 120,
              "keys": {
                "DEFAULT": 0.35,
                "PET": 0.175
              }
            }
          }
        },
        "172-176": {
          "blocks": {
            "PACKED_ICE": {
              "hardness": 170,
              "data": 0,
              "replace": 120,
              "keys": {
                "DEFAULT": 0.35,
                "PET": 0.175
              }
            }
          }
        },
        "167-171": {
          "blocks": {
            "PACKED_ICE": {
              "hardness": 180,
              "data": 0,
              "replace": 120,
              "keys": {
                "DEFAULT": 0.35,
                "PET": 0.175
              }
            }
          }
        },
        "162-166": {
          "blocks": {
            "PACKED_ICE": {
              "hardness": 200,
              "data": 0,
              "replace": 120,
              "keys": {
                "DEFAULT": 0.35,
                "PET": 0.175
              }
            }
          }
        },
        "157-161": {
          "blocks": {
            "PACKED_ICE": {
              "hardness": 300,
              "data": 0,
              "replace": 120,
              "keys": {
                "DEFAULT": 0.35,
                "PET": 0.175
              }
            }
          }
        },
        "152-156": {
          "blocks": {
            "PACKED_ICE": {
              "hardness": 400,
              "data": 0,
              "replace": 120,
              "keys": {
                "DEFAULT": 0.35,
                "PET": 0.175
              }
            }
          }
        },
        "147-151": {
          "blocks": {
            "PACKED_ICE": {
              "hardness": 450,
              "data": 0,
              "replace": 120,
              "keys": {
                "DEFAULT": 0.35,
                "PET": 0.175
              }
            }
          }
        },
        "142-146": {
          "blocks": {
            "PACKED_ICE": {
              "hardness": 500,
              "data": 0,
              "replace": 120,
              "keys": {
                "DEFAULT": 0.35,
                "PET": 0.175
              }
            }
          }
        },
        "137-141": {
          "blocks": {
            "PACKED_ICE": {
              "hardness": 600,
              "data": 0,
              "replace": 120,
              "keys": {
                "DEFAULT": 0.35,
                "PET": 0.175
              }
            }
          }
        },
        "132-136": {
          "blocks": {
            "PACKED_ICE": {
              "hardness": 800,
              "data": 0,
              "replace": 120,
              "keys": {
                "DEFAULT": 0.35,
                "PET": 0.175
              }
            }
          }
        },
        "127-131": {
          "blocks": {
            "PACKED_ICE": {
              "hardness": 1000,
              "data": 0,
              "replace": 120,
              "keys": {
                "DEFAULT": 0.35,
                "PET": 0.175
              }
            }
          }
        },
        "122-126": {
          "blocks": {
            "PACKED_ICE": {
              "hardness": 1250,
              "data": 0,
              "replace": 120,
              "keys": {
                "DEFAULT": 0.35,
                "PET": 0.175
              }
            }
          }
        },
        "117-121": {
          "blocks": {
            "PACKED_ICE": {
              "hardness": 1500,
              "data": 0,
              "replace": 120,
              "keys": {
                "DEFAULT": 0.35,
                "PET": 0.175
              }
            }
          }
        },
        "112-116": {
          "blocks": {
            "PACKED_ICE": {
              "hardness": 1600,
              "data": 0,
              "replace": 120,
              "keys": {
                "DEFAULT": 0.35,
                "PET": 0.175
              }
            }
          }
        },
        "107-111": {
          "blocks": {
            "PACKED_ICE": {
              "hardness": 1700,
              "data": 0,
              "replace": 120,
              "keys": {
                "DEFAULT": 0.35,
                "PET": 0.175
              }
            }
          }
        },
        "102-106": {
          "blocks": {
            "PACKED_ICE": {
              "hardness": 1800,
              "data": 0,
              "replace": 120,
              "keys": {
                "DEFAULT": 0.35,
                "PET": 0.175
              }
            }
          }
        },
        "97-101": {
          "blocks": {
            "PACKED_ICE": {
              "hardness": 1900,
              "data": 0,
              "replace": 120,
              "keys": {
                "DEFAULT": 0.35,
                "PET": 0.175
              }
            }
          }
        },
        "91-96": {
          "blocks": {
            "PACKED_ICE": {
              "hardness": 2000,
              "data": 0,
              "replace": 120,
              "keys": {
                "DEFAULT": 0.35,
                "PET": 0.175
              }
            }
          }
        }
      }
    },
    "4": {
      "layers": {
        "175-205": {
          "blocks": {
            "RED_SANDSTONE": {
              "hardness": 25,
              "data": 0,
              "replace": 120,
              "keys": {
                "DEFAULT": 0.4,
                "PET": 0.2
              }
            }
          }
        },
        "170-174": {
          "blocks": {
            "RED_SANDSTONE": {
              "hardness": 50,
              "data": 0,
              "replace": 120,
              "keys": {
                "DEFAULT": 0.4,
                "PET": 0.2
              }
            }
          }
        },
        "165-169": {
          "blocks": {
            "RED_SANDSTONE": {
              "hardness": 75,
              "data": 0,
              "replace": 120,
              "keys": {
                "DEFAULT": 0.4,
                "PET": 0.2
              }
            }
          }
        },
        "160-164": {
          "blocks": {
            "RED_SANDSTONE": {
              "hardness": 100,
              "data": 0,
              "replace": 120,
              "keys": {
                "DEFAULT": 0.4,
                "PET": 0.2
              }
            }
          }
        },
        "155-159": {
          "blocks": {
            "RED_SANDSTONE": {
              "hardness": 125,
              "data": 0,
              "replace": 120,
              "keys": {
                "DEFAULT": 0.4,
                "PET": 0.2
              }
            }
          }
        },
        "150-154": {
          "blocks": {
            "RED_SANDSTONE": {
              "hardness": 150,
              "data": 0,
              "replace": 120,
              "keys": {
                "DEFAULT": 0.4,
                "PET": 0.2
              }
            }
          }
        },
        "145-149": {
          "blocks": {
            "RED_SANDSTONE": {
              "hardness": 175,
              "data": 0,
              "replace": 120,
              "keys": {
                "DEFAULT": 0.4,
                "PET": 0.2
              }
            }
          }
        },
        "140-144": {
          "blocks": {
            "RED_SANDSTONE": {
              "hardness": 200,
              "data": 0,
              "replace": 120,
              "keys": {
                "DEFAULT": 0.4,
                "PET": 0.2
              }
            }
          }
        },
        "135-139": {
          "blocks": {
            "RED_SANDSTONE": {
              "hardness": 225,
              "data": 0,
              "replace": 120,
              "keys": {
                "DEFAULT": 0.4,
                "PET": 0.2
              }
            }
          }
        },
        "130-134": {
          "blocks": {
            "RED_SANDSTONE": {
              "hardness": 250,
              "data": 0,
              "replace": 120,
              "keys": {
                "DEFAULT": 0.4,
                "PET": 0.2
              }
            }
          }
        },
        "125-129": {
          "blocks": {
            "RED_SANDSTONE": {
              "hardness": 275,
              "data": 0,
              "replace": 120,
              "keys": {
                "DEFAULT": 0.4,
                "PET": 0.2
              }
            }
          }
        },
        "120-124": {
          "blocks": {
            "RED_SANDSTONE": {
              "hardness": 300,
              "data": 0,
              "replace": 120,
              "keys": {
                "DEFAULT": 0.4,
                "PET": 0.2
              }
            }
          }
        },
        "115-119": {
          "blocks": {
            "RED_SANDSTONE": {
              "hardness": 350,
              "data": 0,
              "replace": 120,
              "keys": {
                "DEFAULT": 0.4,
                "PET": 0.2
              }
            }
          }
        },
        "110-114": {
          "blocks": {
            "RED_SANDSTONE": {
              "hardness": 400,
              "data": 0,
              "replace": 120,
              "keys": {
                "DEFAULT": 0.4,
                "PET": 0.2
              }
            }
          }
        },
        "105-109": {
          "blocks": {
            "RED_SANDSTONE": {
              "hardness": 500,
              "data": 0,
              "replace": 120,
              "keys": {
                "DEFAULT": 0.4,
                "PET": 0.2
              }
            }
          }
        },
        "100-104": {
          "blocks": {
            "RED_SANDSTONE": {
              "hardness": 750,
              "data": 0,
              "replace": 120,
              "keys": {
                "DEFAULT": 0.4,
                "PET": 0.2
              }
            }
          }
        },
        "95-99": {
          "blocks": {
            "RED_SANDSTONE": {
              "hardness": 950,
              "data": 0,
              "replace": 120,
              "keys": {
                "DEFAULT": 0.4,
                "PET": 0.2
              }
            }
          }
        },
        "90-94": {
          "blocks": {
            "RED_SANDSTONE": {
              "hardness": 1100,
              "data": 0,
              "replace": 120,
              "keys": {
                "DEFAULT": 0.4,
                "PET": 0.2
              }
            }
          }
        },
        "85-89": {
          "blocks": {
            "RED_SANDSTONE": {
              "hardness": 1300,
              "data": 0,
              "replace": 120,
              "keys": {
                "DEFAULT": 0.4,
                "PET": 0.2
              }
            }
          }
        },
        "80-84": {
          "blocks": {
            "RED_SANDSTONE": {
              "hardness": 1500,
              "data": 0,
              "replace": 120,
              "keys": {
                "DEFAULT": 0.4,
                "PET": 0.2
              }
            }
          }
        },
        "75-79": {
          "blocks": {
            "RED_SANDSTONE": {
              "hardness": 1700,
              "data": 0,
              "replace": 120,
              "keys": {
                "DEFAULT": 0.4,
                "PET": 0.2
              }
            }
          }
        },
        "70-74": {
          "blocks": {
            "RED_SANDSTONE": {
              "hardness": 1900,
              "data": 0,
              "replace": 120,
              "keys": {
                "DEFAULT": 0.4,
                "PET": 0.2
              }
            }
          }
        },
        "65-69": {
          "blocks": {
            "RED_SANDSTONE": {
              "hardness": 2100,
              "data": 0,
              "replace": 120,
              "keys": {
                "DEFAULT": 0.4,
                "PET": 0.2
              }
            }
          }
        },
        "60-64": {
          "blocks": {
            "RED_SANDSTONE": {
              "hardness": 2300,
              "data": 0,
              "replace": 120,
              "keys": {
                "DEFAULT": 0.4,
                "PET": 0.2
              }
            }
          }
        },
        "55-59": {
          "blocks": {
            "RED_SANDSTONE": {
              "hardness": 2500,
              "data": 0,
              "replace": 120,
              "keys": {
                "DEFAULT": 0.4,
                "PET": 0.2
              }
            }
          }
        }
      }
    },
    "5": {
      "layers": {
        "160-179": {
          "blocks": {
            "COBBLESTONE": {
              "hardness": 35,
              "data": 0,
              "replace": 120,
              "keys": {
                "DEFAULT": 0.45,
                "PET": 0.225
              }
            },
            "STONE": {
              "hardness": 35,
              "data": 0,
              "replace": 120,
              "keys": {
                "DEFAULT": 0.45,
                "PET": 0.225
              }
            },
            "MOSSY_COBBLESTONE": {
              "hardness": 35,
              "data": 0,
              "replace": 120,
              "keys": {
                "DEFAULT": 0.45,
                "PET": 0.225
              }
            }
          }
        },
        "155-159": {
          "blocks": {
            "COBBLESTONE": {
              "hardness": 80,
              "data": 0,
              "replace": 120,
              "keys": {
                "DEFAULT": 0.45,
                "PET": 0.225
              }
            },
            "STONE": {
              "hardness": 80,
              "data": 0,
              "replace": 120,
              "keys": {
                "DEFAULT": 0.45,
                "PET": 0.225
              }
            },
            "MOSSY_COBBLESTONE": {
              "hardness": 80,
              "data": 0,
              "replace": 120,
              "keys": {
                "DEFAULT": 0.45,
                "PET": 0.225
              }
            }
          }
        },
        "150-154": {
          "blocks": {
            "COBBLESTONE": {
              "hardness": 150,
              "data": 0,
              "replace": 120,
              "keys": {
                "DEFAULT": 0.45,
                "PET": 0.225
              }
            },
            "STONE": {
              "hardness": 150,
              "data": 0,
              "replace": 120,
              "keys": {
                "DEFAULT": 0.45,
                "PET": 0.225
              }
            },
            "MOSSY_COBBLESTONE": {
              "hardness": 150,
              "data": 0,
              "replace": 120,
              "keys": {
                "DEFAULT": 0.45,
                "PET": 0.225
              }
            }
          }
        },
        "145-149": {
          "blocks": {
            "STONE": {
              "hardness": 200,
              "data": 0,
              "replace": 120,
              "keys": {
                "DEFAULT": 0.45,
                "PET": 0.225
              }
            }
          }
        },
        "140-144": {
          "blocks": {
            "STONE": {
              "hardness": 250,
              "data": 0,
              "replace": 120,
              "keys": {
                "DEFAULT": 0.45,
                "PET": 0.225
              }
            }
          }
        },
        "135-139": {
          "blocks": {
            "STONE": {
              "hardness": 300,
              "data": 0,
              "replace": 120,
              "keys": {
                "DEFAULT": 0.45,
                "PET": 0.225
              }
            }
          }
        },
        "130-134": {
          "blocks": {
            "STONE": {
              "hardness": 350,
              "data": 0,
              "replace": 120,
              "keys": {
                "DEFAULT": 0.45,
                "PET": 0.225
              }
            }
          }
        },
        "125-129": {
          "blocks": {
            "STONE": {
              "hardness": 400,
              "data": 0,
              "replace": 120,
              "keys": {
                "DEFAULT": 0.45,
                "PET": 0.225
              }
            }
          }
        },
        "120-124": {
          "blocks": {
            "STONE": {
              "hardness": 450,
              "data": 0,
              "replace": 120,
              "keys": {
                "DEFAULT": 0.45,
                "PET": 0.225
              }
            }
          }
        },
        "115-119": {
          "blocks": {
            "STONE": {
              "hardness": 500,
              "data": 0,
              "replace": 120,
              "keys": {
                "DEFAULT": 0.45,
                "PET": 0.225
              }
            }
          }
        },
        "110-114": {
          "blocks": {
            "STONE": {
              "hardness": 550,
              "data": 0,
              "replace": 120,
              "keys": {
                "DEFAULT": 0.45,
                "PET": 0.225
              }
            }
          }
        },
        "105-109": {
          "blocks": {
            "STONE": {
              "hardness": 600,
              "data": 0,
              "replace": 120,
              "keys": {
                "DEFAULT": 0.45,
                "PET": 0.225
              }
            }
          }
        },
        "100-104": {
          "blocks": {
            "STONE": {
              "hardness": 650,
              "data": 0,
              "replace": 120,
              "keys": {
                "DEFAULT": 0.45,
                "PET": 0.225
              }
            }
          }
        },
        "95-99": {
          "blocks": {
            "STONE": {
              "hardness": 700,
              "data": 0,
              "replace": 120,
              "keys": {
                "DEFAULT": 0.45,
                "PET": 0.225
              }
            }
          }
        },
        "90-94": {
          "blocks": {
            "STONE": {
              "hardness": 750,
              "data": 0,
              "replace": 120,
              "keys": {
                "DEFAULT": 0.45,
                "PET": 0.225
              }
            }
          }
        },
        "85-89": {
          "blocks": {
            "STONE": {
              "hardness": 800,
              "data": 0,
              "replace": 120,
              "keys": {
                "DEFAULT": 0.45,
                "PET": 0.225
              }
            }
          }
        },
        "80-84": {
          "blocks": {
            "STONE": {
              "hardness": 1000,
              "data": 0,
              "replace": 120,
              "keys": {
                "DEFAULT": 0.45,
                "PET": 0.225
              }
            }
          }
        },
        "75-79": {
          "blocks": {
            "STONE": {
              "hardness": 1500,
              "data": 0,
              "replace": 120,
              "keys": {
                "DEFAULT": 0.45,
                "PET": 0.225
              }
            }
          }
        },
        "70-74": {
          "blocks": {
            "STONE": {
              "hardness": 2000,
              "data": 0,
              "replace": 120,
              "keys": {
                "DEFAULT": 0.45,
                "PET": 0.225
              }
            }
          }
        },
        "65-69": {
          "blocks": {
            "STONE": {
              "hardness": 2250,
              "data": 0,
              "replace": 120,
              "keys": {
                "DEFAULT": 0.45,
                "PET": 0.225
              }
            }
          }
        },
        "60-64": {
          "blocks": {
            "STONE": {
              "hardness": 2500,
              "data": 0,
              "replace": 120,
              "keys": {
                "DEFAULT": 0.45,
                "PET": 0.225
              }
            }
          }
        },
        "55-59": {
          "blocks": {
            "STONE": {
              "hardness": 2750,
              "data": 0,
              "replace": 120,
              "keys": {
                "DEFAULT": 0.45,
                "PET": 0.225
              }
            }
          }
        },
        "50-54": {
          "blocks": {
            "STONE": {
              "hardness": 3000,
              "data": 0,
              "replace": 120,
              "keys": {
                "DEFAULT": 0.45,
                "PET": 0.225
              }
            }
          }
        }
      }
    },
    "6": {
      "layers": {
        "143-147": {
          "blocks": {
            "HARD_CLAY": {
              "hardness": 40,
              "data": 0,
              "replace": 120,
              "keys": {
                "DEFAULT": 0.5,
                "PET": 0.25
              }
            },
            "STAINED_CLAY": {
              "hardness": 40,
              "data": 8,
              "replace": 120,
              "keys": {
                "DEFAULT": 0.5,
                "PET": 0.25
              }
            }
          }
        },
        "138-142": {
          "blocks": {
            "HARD_CLAY": {
              "hardness": 80,
              "data": 0,
              "replace": 120,
              "keys": {
                "DEFAULT": 0.5,
                "PET": 0.25
              }
            },
            "STAINED_CLAY": {
              "hardness": 80,
              "data": 8,
              "replace": 120,
              "keys": {
                "DEFAULT": 0.5,
                "PET": 0.25
              }
            }
          }
        },
        "133-137": {
          "blocks": {
            "HARD_CLAY": {
              "hardness": 150,
              "data": 0,
              "replace": 120,
              "keys": {
                "DEFAULT": 0.5,
                "PET": 0.25
              }
            },
            "STAINED_CLAY": {
              "hardness": 150,
              "data": 8,
              "replace": 120,
              "keys": {
                "DEFAULT": 0.5,
                "PET": 0.25
              }
            }
          }
        },
        "128-132": {
          "blocks": {
            "HARD_CLAY": {
              "hardness": 180,
              "data": 0,
              "replace": 120,
              "keys": {
                "DEFAULT": 0.5,
                "PET": 0.25
              }
            },
            "STAINED_CLAY": {
              "hardness": 180,
              "data": 8,
              "replace": 120,
              "keys": {
                "DEFAULT": 0.5,
                "PET": 0.25
              }
            }
          }
        },
        "123-127": {
          "blocks": {
            "HARD_CLAY": {
              "hardness": 200,
              "data": 0,
              "replace": 120,
              "keys": {
                "DEFAULT": 0.5,
                "PET": 0.25
              }
            },
            "STAINED_CLAY": {
              "hardness": 200,
              "data": 8,
              "replace": 120,
              "keys": {
                "DEFAULT": 0.5,
                "PET": 0.25
              }
            }
          }
        },
        "118-122": {
          "blocks": {
            "STAINED_CLAY": {
              "hardness": 250,
              "data": 8,
              "replace": 120,
              "keys": {
                "DEFAULT": 0.5,
                "PET": 0.25
              }
            }
          }
        },
        "113-117": {
          "blocks": {
            "STAINED_CLAY": {
              "hardness": 250,
              "data": 8,
              "replace": 120,
              "keys": {
                "DEFAULT": 0.5,
                "PET": 0.25
              }
            }
          }
        },
        "108-112": {
          "blocks": {
            "STAINED_CLAY": {
              "hardness": 400,
              "data": 8,
              "replace": 120,
              "keys": {
                "DEFAULT": 0.5,
                "PET": 0.25
              }
            }
          }
        },
        "103-107": {
          "blocks": {
            "STAINED_CLAY": {
              "hardness": 450,
              "data": 8,
              "replace": 120,
              "keys": {
                "DEFAULT": 0.5,
                "PET": 0.25
              }
            }
          }
        },
        "98-102": {
          "blocks": {
            "STAINED_CLAY": {
              "hardness": 500,
              "data": 8,
              "replace": 120,
              "keys": {
                "DEFAULT": 0.5,
                "PET": 0.25
              }
            }
          }
        },
        "93-97": {
          "blocks": {
            "STAINED_CLAY": {
              "hardness": 600,
              "data": 8,
              "replace": 120,
              "keys": {
                "DEFAULT": 0.5,
                "PET": 0.25
              }
            }
          }
        },
        "88-92": {
          "blocks": {
            "STAINED_CLAY": {
              "hardness": 750,
              "data": 8,
              "replace": 120,
              "keys": {
                "DEFAULT": 0.5,
                "PET": 0.25
              }
            }
          }
        },
        "83-87": {
          "blocks": {
            "STAINED_CLAY": {
              "hardness": 1200,
              "data": 8,
              "replace": 120,
              "keys": {
                "DEFAULT": 0.5,
                "PET": 0.25
              }
            }
          }
        },
        "78-82": {
          "blocks": {
            "STAINED_CLAY": {
              "hardness": 1250,
              "data": 8,
              "replace": 120,
              "keys": {
                "DEFAULT": 0.5,
                "PET": 0.25
              }
            }
          }
        },
        "73-77": {
          "blocks": {
            "STAINED_CLAY": {
              "hardness": 1300,
              "data": 8,
              "replace": 120,
              "keys": {
                "DEFAULT": 0.5,
                "PET": 0.25
              }
            }
          }
        },
        "68-72": {
          "blocks": {
            "STAINED_CLAY": {
              "hardness": 1400,
              "data": 8,
              "replace": 120,
              "keys": {
                "DEFAULT": 0.5,
                "PET": 0.25
              }
            }
          }
        },
        "63-67": {
          "blocks": {
            "STAINED_CLAY": {
              "hardness": 1750,
              "data": 8,
              "replace": 120,
              "keys": {
                "DEFAULT": 0.5,
                "PET": 0.25
              }
            }
          }
        },
        "58-62": {
          "blocks": {
            "STAINED_CLAY": {
              "hardness": 2000,
              "data": 8,
              "replace": 120,
              "keys": {
                "DEFAULT": 0.5,
                "PET": 0.25
              }
            }
          }
        },
        "53-57": {
          "blocks": {
            "STAINED_CLAY": {
              "hardness": 2250,
              "data": 8,
              "replace": 120,
              "keys": {
                "DEFAULT": 0.5,
                "PET": 0.25
              }
            }
          }
        },
        "48-52": {
          "blocks": {
            "STAINED_CLAY": {
              "hardness": 2500,
              "data": 8,
              "replace": 120,
              "keys": {
                "DEFAULT": 0.5,
                "PET": 0.25
              }
            }
          }
        },
        "43-47": {
          "blocks": {
            "STAINED_CLAY": {
              "hardness": 3000,
              "data": 8,
              "replace": 120,
              "keys": {
                "DEFAULT": 0.5,
                "PET": 0.25
              }
            }
          }
        },
        "38-42": {
          "blocks": {
            "STAINED_CLAY": {
              "hardness": 3250,
              "data": 8,
              "replace": 120,
              "keys": {
                "DEFAULT": 0.5,
                "PET": 0.25
              }
            }
          }
        },
        "35-37": {
          "blocks": {
            "STAINED_CLAY": {
              "hardness": 4000,
              "data": 8,
              "replace": 120,
              "keys": {
                "DEFAULT": 0.5,
                "PET": 0.25
              }
            }
          }
        }
      }
    },
    "7": {
      "layers": {
        "147-151": {
          "blocks": {
            "ENDER_STONE": {
              "hardness": 45,
              "data": 0,
              "replace": 120,
              "keys": {
                "DEFAULT": 0.5,
                "PET": 0.25
              }
            },
            "END_BRICKS": {
              "hardness": 45,
              "data": 0,
              "replace": 120,
              "keys": {
                "DEFAULT": 0.5,
                "PET": 0.25
              }
            },
            "PURPUR_BLOCK": {
              "hardness": 45,
              "data": 0,
              "replace": 120,
              "keys": {
                "DEFAULT": 0.5,
                "PET": 0.25
              }
            },
            "PURPUR_PILLAR": {
              "hardness": 45,
              "data": 0,
              "replace": 120,
              "keys": {
                "DEFAULT": 0.5,
                "PET": 0.25
              }
            }
          }
        },
        "142-146": {
          "blocks": {
            "ENDER_STONE": {
              "hardness": 90,
              "data": 0,
              "replace": 120,
              "keys": {
                "DEFAULT": 0.5,
                "PET": 0.25
              }
            },
            "END_BRICKS": {
              "hardness": 90,
              "data": 0,
              "replace": 120,
              "keys": {
                "DEFAULT": 0.5,
                "PET": 0.25
              }
            },
            "PURPUR_BLOCK": {
              "hardness": 90,
              "data": 0,
              "replace": 120,
              "keys": {
                "DEFAULT": 0.5,
                "PET": 0.25
              }
            },
            "PURPUR_PILLAR": {
              "hardness": 90,
              "data": 0,
              "replace": 120,
              "keys": {
                "DEFAULT": 0.5,
                "PET": 0.25
              }
            }
          }
        },
        "137-141": {
          "blocks": {
            "ENDER_STONE": {
              "hardness": 120,
              "data": 0,
              "replace": 120,
              "keys": {
                "DEFAULT": 0.5,
                "PET": 0.25
              }
            },
            "END_BRICKS": {
              "hardness": 120,
              "data": 0,
              "replace": 120,
              "keys": {
                "DEFAULT": 0.5,
                "PET": 0.25
              }
            },
            "PURPUR_BLOCK": {
              "hardness": 120,
              "data": 0,
              "replace": 120,
              "keys": {
                "DEFAULT": 0.5,
                "PET": 0.25
              }
            },
            "PURPUR_PILLAR": {
              "hardness": 120,
              "data": 0,
              "replace": 120,
              "keys": {
                "DEFAULT": 0.5,
                "PET": 0.25
              }
            }
          }
        },
        "132-136": {
          "blocks": {
            "ENDER_STONE": {
              "hardness": 145,
              "data": 0,
              "replace": 120,
              "keys": {
                "DEFAULT": 0.5,
                "PET": 0.25
              }
            },
            "END_BRICKS": {
              "hardness": 145,
              "data": 0,
              "replace": 120,
              "keys": {
                "DEFAULT": 0.5,
                "PET": 0.25
              }
            },
            "PURPUR_BLOCK": {
              "hardness": 145,
              "data": 0,
              "replace": 120,
              "keys": {
                "DEFAULT": 0.5,
                "PET": 0.25
              }
            },
            "PURPUR_PILLAR": {
              "hardness": 145,
              "data": 0,
              "replace": 120,
              "keys": {
                "DEFAULT": 0.5,
                "PET": 0.25
              }
            }
          }
        },
        "127-131": {
          "blocks": {
            "ENDER_STONE": {
              "hardness": 160,
              "data": 0,
              "replace": 120,
              "keys": {
                "DEFAULT": 0.5,
                "PET": 0.25
              }
            },
            "END_BRICKS": {
              "hardness": 160,
              "data": 0,
              "replace": 120,
              "keys": {
                "DEFAULT": 0.5,
                "PET": 0.25
              }
            },
            "PURPUR_BLOCK": {
              "hardness": 160,
              "data": 0,
              "replace": 120,
              "keys": {
                "DEFAULT": 0.5,
                "PET": 0.25
              }
            },
            "PURPUR_PILLAR": {
              "hardness": 160,
              "data": 0,
              "replace": 120,
              "keys": {
                "DEFAULT": 0.5,
                "PET": 0.25
              }
            }
          }
        },
        "122-126": {
          "blocks": {
            "ENDER_STONE": {
              "hardness": 190,
              "data": 0,
              "replace": 120,
              "keys": {
                "DEFAULT": 0.5,
                "PET": 0.25
              }
            },
            "END_BRICKS": {
              "hardness": 190,
              "data": 0,
              "replace": 120,
              "keys": {
                "DEFAULT": 0.5,
                "PET": 0.25
              }
            },
            "PURPUR_BLOCK": {
              "hardness": 190,
              "data": 0,
              "replace": 120,
              "keys": {
                "DEFAULT": 0.5,
                "PET": 0.25
              }
            },
            "PURPUR_PILLAR": {
              "hardness": 190,
              "data": 0,
              "replace": 120,
              "keys": {
                "DEFAULT": 0.5,
                "PET": 0.25
              }
            }
          }
        },
        "117-121": {
          "blocks": {
            "ENDER_STONE": {
              "hardness": 225,
              "data": 0,
              "replace": 120,
              "keys": {
                "DEFAULT": 0.5,
                "PET": 0.25
              }
            }
          }
        },
        "112-116": {
          "blocks": {
            "ENDER_STONE": {
              "hardness": 250,
              "data": 0,
              "replace": 120,
              "keys": {
                "DEFAULT": 0.5,
                "PET": 0.25
              }
            }
          }
        },
        "107-111": {
          "blocks": {
            "ENDER_STONE": {
              "hardness": 300,
              "data": 0,
              "replace": 120,
              "keys": {
                "DEFAULT": 0.5,
                "PET": 0.25
              }
            }
          }
        },
        "102-106": {
          "blocks": {
            "ENDER_STONE": {
              "hardness": 350,
              "data": 0,
              "replace": 120,
              "keys": {
                "DEFAULT": 0.5,
                "PET": 0.25
              }
            }
          }
        },
        "97-101": {
          "blocks": {
            "ENDER_STONE": {
              "hardness": 450,
              "data": 0,
              "replace": 120,
              "keys": {
                "DEFAULT": 0.5,
                "PET": 0.25
              }
            }
          }
        },
        "92-96": {
          "blocks": {
            "ENDER_STONE": {
              "hardness": 650,
              "data": 0,
              "replace": 120,
              "keys": {
                "DEFAULT": 0.5,
                "PET": 0.25
              }
            }
          }
        },
        "87-91": {
          "blocks": {
            "ENDER_STONE": {
              "hardness": 850,
              "data": 0,
              "replace": 120,
              "keys": {
                "DEFAULT": 0.5,
                "PET": 0.25
              }
            }
          }
        },
        "82-86": {
          "blocks": {
            "ENDER_STONE": {
              "hardness": 1050,
              "data": 0,
              "replace": 120,
              "keys": {
                "DEFAULT": 0.5,
                "PET": 0.25
              }
            }
          }
        },
        "77-81": {
          "blocks": {
            "ENDER_STONE": {
              "hardness": 1250,
              "data": 0,
              "replace": 120,
              "keys": {
                "DEFAULT": 0.5,
                "PET": 0.25
              }
            }
          }
        },
        "72-76": {
          "blocks": {
            "ENDER_STONE": {
              "hardness": 1350,
              "data": 0,
              "replace": 120,
              "keys": {
                "DEFAULT": 0.5,
                "PET": 0.25
              }
            }
          }
        },
        "67-71": {
          "blocks": {
            "ENDER_STONE": {
              "hardness": 1650,
              "data": 0,
              "replace": 120,
              "keys": {
                "DEFAULT": 0.5,
                "PET": 0.25
              }
            }
          }
        },
        "62-66": {
          "blocks": {
            "ENDER_STONE": {
              "hardness": 1950,
              "data": 0,
              "replace": 120,
              "keys": {
                "DEFAULT": 0.5,
                "PET": 0.25
              }
            }
          }
        },
        "57-61": {
          "blocks": {
            "ENDER_STONE": {
              "hardness": 2150,
              "data": 0,
              "replace": 120,
              "keys": {
                "DEFAULT": 0.5,
                "PET": 0.25
              }
            }
          }
        },
        "52-56": {
          "blocks": {
            "ENDER_STONE": {
              "hardness": 2450,
              "data": 0,
              "replace": 120,
              "keys": {
                "DEFAULT": 0.5,
                "PET": 0.25
              }
            }
          }
        },
        "47-51": {
          "blocks": {
            "ENDER_STONE": {
              "hardness": 2750,
              "data": 0,
              "replace": 120,
              "keys": {
                "DEFAULT": 0.5,
                "PET": 0.25
              }
            }
          }
        },
        "42-46": {
          "blocks": {
            "ENDER_STONE": {
              "hardness": 3000,
              "data": 0,
              "replace": 120,
              "keys": {
                "DEFAULT": 0.5,
                "PET": 0.25
              }
            }
          }
        },
        "37-41": {
          "blocks": {
            "ENDER_STONE": {
              "hardness": 3250,
              "data": 0,
              "replace": 120,
              "keys": {
                "DEFAULT": 0.5,
                "PET": 0.25
              }
            }
          }
        },
        "32-36": {
          "blocks": {
            "ENDER_STONE": {
              "hardness": 3500,
              "data": 0,
              "replace": 120,
              "keys": {
                "DEFAULT": 0.5,
                "PET": 0.25
              }
            }
          }
        },
        "27-31": {
          "blocks": {
            "ENDER_STONE": {
              "hardness": 4000,
              "data": 0,
              "replace": 120,
              "keys": {
                "DEFAULT": 0.5,
                "PET": 0.25
              }
            }
          }
        },
        "24-26": {
          "blocks": {
            "ENDER_STONE": {
              "hardness": 4500,
              "data": 0,
              "replace": 120,
              "keys": {
                "DEFAULT": 0.5,
                "PET": 0.25
              }
            }
          }
        }
      }
    }
  }
}