{
  "trampolinePlace": {
    "radius": 0.5,
    "angles": 25,
    "color": "BLUE_LIGHT",
    "location": {
      "name": "jump",
      "offset": {
        "x": 0.5,
        "y": -5,
        "z": 0.5
      }
    }
  },
  "locations": {
    "1": {
      "banner": {
        "content": "treasures.map.trampoline.content",
        "opacity": 0,
        "resizeLine": {
          "0": 0.4
        },
        "location": {
          "name": "jump",
          "yaw": 0,
          "pitch": -90,
          "offset": {
            "x": 0.5,
            "y": -0.9,
            "z": 0.3
          }
        }
      }
    },
    "2": {
      "banner": {
        "content": "treasures.map.trampoline.content",
        "opacity": 0,
        "resizeLine": {
          "0": 0.4
        },
        "location": {
          "name": "jump",
          "yaw": 0,
          "pitch": -90,
          "offset": {
            "x": 0.5,
            "y": -0.9,
            "z": 0.3
          }
        }
      }
    },
    "3": {
      "banner": {
        "content": "treasures.map.trampoline.content",
        "opacity": 0,
        "resizeLine": {
          "0": 0.4
        },
        "location": {
          "name": "jump",
          "yaw": 180,
          "pitch": -90,
          "offset": {
            "x": 0.5,
            "y": -0.9,
            "z": 0.7
          }
        }
      }
    },
    "4": {
      "banner": {
        "content": "treasures.map.trampoline.content",
        "opacity": 0,
        "resizeLine": {
          "0": 0.4
        },
        "location": {
          "name": "jump",
          "yaw": 0,
          "pitch": -90,
          "offset": {
            "x": 0.5,
            "y": -0.9,
            "z": 0.3
          }
        }
      }
    },
    "5": {
      "banner": {
        "content": "treasures.map.trampoline.content",
        "opacity": 0,
        "resizeLine": {
          "0": 0.4
        },
        "location": {
          "name": "jump",
          "yaw": 90,
          "pitch": -90,
          "offset": {
            "x": 0.75,
            "y": -0.9,
            "z": 0.5
          }
        }
      }
    },
    "6": {
      "banner": {
        "content": "treasures.map.trampoline.content",
        "opacity": 0,
        "resizeLine": {
          "0": 0.4
        },
        "location": {
          "name": "jump",
          "yaw": 0,
          "pitch": -90,
          "offset": {
            "x": 0.5,
            "y": -0.9,
            "z": 0.3
          }
        }
      }
    },
    "7": {
      "banner": {
        "content": "treasures.map.trampoline.content",
        "opacity": 0,
        "resizeLine": {
          "0": 0.4
        },
        "location": {
          "name": "jump",
          "yaw": 0,
          "pitch": -90,
          "offset": {
            "x": 0.5,
            "y": -0.9,
            "z": 0.3
          }
        }
      }
    }
  }
}